mkpipe_loader_sqlserver/__init__.py
mkpipe_loader_sqlserver/jars/com.microsoft.sqlserver_mssql-jdbc-12.8.1.jre11.jar
mkpipe_loader_sqlserver-0.1.1.dist-info/LICENSE
mkpipe_loader_sqlserver-0.1.1.dist-info/METADATA
mkpipe_loader_sqlserver-0.1.1.dist-info/WHEEL
mkpipe_loader_sqlserver-0.1.1.dist-info/entry_points.txt
mkpipe_loader_sqlserver-0.1.1.dist-info/top_level.txt
mkpipe_loader_sqlserver-0.1.1.dist-info/RECORD
